DUI/__init__.py
DUI/Frames/Alert.py
DUI/Frames/Frame.py
DUI/Frames/Listener.py
DUI/Frames/Window.py
DUI/Frames/__init__.py
DUI/Widgets/Button.py
DUI/Widgets/Text.py
DUI/Widgets/Widget.py
DUI/Widgets/__init__.py
DUI/bin/__init__.py
DUI/bin/util.py
DUI-1.0.1.dist-info/LICENSE
DUI-1.0.1.dist-info/METADATA
DUI-1.0.1.dist-info/WHEEL
DUI-1.0.1.dist-info/top_level.txt
DUI-1.0.1.dist-info/RECORD
